PyMicrosoftSQL/__init__.py
PyMicrosoftSQL/async_sql_event_manager.py
PyMicrosoftSQL/connection_async_linux.py
PyMicrosoftSQL/connection_async_mac.py
PyMicrosoftSQL/connection_async_win.py
PyMicrosoftSQL/connection_linux.py
PyMicrosoftSQL/connection_mac.py
PyMicrosoftSQL/connection_win.py
PyMicrosoftSQL/constants.py
PyMicrosoftSQL/cursor.py
PyMicrosoftSQL/cursor_async_test.py
PyMicrosoftSQL/helper.py
PyMicrosoftSQL/mac_setup.py
PyMicrosoftSQL/row.py
PyMicrosoftSQL/linux_so_files/lib/libSqlAsyncEventHandler.so
PyMicrosoftSQL/linux_so_files/lib/libmsodbcsql-18.4.so.1.1
PyMicrosoftSQL/linux_so_files/lib/libodbcinst.so.2
PyMicrosoftSQL/linux_so_files/share/resources/en_US/msodbcsqlr18.rll
PyMicrosoftSQL/mac_dylibs/arm64/main_lib.py
PyMicrosoftSQL/mac_dylibs/arm64/lib/libcrypto.3.dylib
PyMicrosoftSQL/mac_dylibs/arm64/lib/libltdl.7.dylib
PyMicrosoftSQL/mac_dylibs/arm64/lib/libmsodbcsql.18.dylib
PyMicrosoftSQL/mac_dylibs/arm64/lib/libodbcinst.2.dylib
PyMicrosoftSQL/mac_dylibs/arm64/lib/libssl.3.dylib
PyMicrosoftSQL/mac_dylibs/arm64/share/doc/msodbcsql18/LICENSE.txt
PyMicrosoftSQL/mac_dylibs/arm64/share/doc/msodbcsql18/RELEASE_NOTES
PyMicrosoftSQL/mac_dylibs/arm64/share/msodbcsql18/resources/en_US/msodbcsqlr18.rll
PyMicrosoftSQL/mac_dylibs/x86_64/main_lib.py
PyMicrosoftSQL/mac_dylibs/x86_64/lib/libSqlAsyncEventHandler.dylib
PyMicrosoftSQL/mac_dylibs/x86_64/lib/libSqlAsyncEventHandler.so
PyMicrosoftSQL/mac_dylibs/x86_64/lib/libcrypto.3.dylib
PyMicrosoftSQL/mac_dylibs/x86_64/lib/libltdl.7.dylib
PyMicrosoftSQL/mac_dylibs/x86_64/lib/libmsodbcsql.18.dylib
PyMicrosoftSQL/mac_dylibs/x86_64/lib/libodbc.2.dylib
PyMicrosoftSQL/mac_dylibs/x86_64/lib/libodbc.a
PyMicrosoftSQL/mac_dylibs/x86_64/lib/libodbccr.2.dylib
PyMicrosoftSQL/mac_dylibs/x86_64/lib/libodbccr.a
PyMicrosoftSQL/mac_dylibs/x86_64/lib/libodbcinst.2.dylib
PyMicrosoftSQL/mac_dylibs/x86_64/lib/libodbcinst.a
PyMicrosoftSQL/mac_dylibs/x86_64/lib/libssl.3.dylib
PyMicrosoftSQL/mac_dylibs/x86_64/lib/ossl-modules/legacy.dylib
PyMicrosoftSQL-0.1.1.dist-info/LICENSE.txt
PyMicrosoftSQL-0.1.1.dist-info/METADATA
PyMicrosoftSQL-0.1.1.dist-info/WHEEL
PyMicrosoftSQL-0.1.1.dist-info/top_level.txt
PyMicrosoftSQL-0.1.1.dist-info/RECORD
