Metadata-Version: 2.1
Name: PyMicrosoftSQL
Version: 0.1.1
Summary: A simple Python SQL driver for Microsoft SQL Server
Home-page: https://github.com/microsoft/python-sql-driver
Author: Microsoft Corporation
Author-email: pysqldriver@microsoft.com
Classifier: Programming Language :: Python :: 3
Classifier: License :: OSI Approved :: MIT License
Classifier: Operating System :: OS Independent
Requires-Python: >=3.6
License-File: LICENSE.txt
Requires-Dist: tabulate
